[
    {
      "nome": "Maria",
      "sobrenome": "Silva",
      "empresa": "Empresa A",
      "pais": "Brasil",
      "endereco": "Rua A, 123",
      "numero": "123",
      "cidade": "São Paulo",
      "estado": "São Paulo",
      "cep": "01234-567",
      "telefone": "+55 (11) 1234-5678",
      "email": "maria.silva@empresa.com"
    },
    {
      "nome": "José",
      "sobrenome": "Santos",
      "empresa": "Empresa B",
      "pais": "Brasil",
      "endereco": "Rua B, 456",
      "numero": "456",
      "cidade": "Rio de Janeiro",
      "estado": "Rio de Janeiro",
      "cep": "98765-432",
      "telefone": "+55 (21) 9876-5432",
      "email": "jose.santos@empresa.com"
    },
    {
      "nome": "Carla",
      "sobrenome": "Ferreira",
      "empresa": "Empresa C",
      "pais": "Brasil",
      "endereco": "Av. C, 789",
      "numero": "789",
      "cidade": "Belo Horizonte",
      "estado": "Minas Gerais",
      "cep": "34567-890",
      "telefone": "+55 (31) 1234-5678",
      "email": "carla.ferreira@empresa.com"
    },
    {
      "nome": "Paulo",
      "sobrenome": "Mendes",
      "empresa": "Empresa D",
      "pais": "Brasil",
      "endereco": "Rua D, 111",
      "numero": "111",
      "cidade": "Porto Alegre",
      "estado": "Rio Grande do Sul",
      "cep": "54321-098",
      "telefone": "+55 (51) 9876-5432",
      "email": "paulo.mendes@empresa.com"
    },
    {
      "nome": "Camila",
      "sobrenome": "Oliveira",
      "empresa": "Empresa E",
      "pais": "Brasil",
      "endereco": "Rua E, 222",
      "numero": "222",
      "cidade": "Fortaleza",
      "estado": "Ceará",
      "cep": "67890-123",
      "telefone": "+55 (85) 1234-5678",
      "email": "camila.oliveira@empresa.com"
    }
  ]